<?xml version="1.0" encoding="UTF-8" standalone="no"?><paper><id>15</id><title>2012年浙江行测真题卷</title><num>95</num><subjects><item><itemNumber>1</itemNumber><itemTitle>房产税并非能直接降低房价，但是对房价预期起作用，________在于建立合理的长效税收机制，对于促进商品房市场机制的形成必不可少。今后应征收存量房的房产税，以逐步________土地出让金，这一步应及早进行。
填入划横线部分最恰当的一项是：
</itemTitle><sectionA>目的   废除</sectionA><sectionB>意义   取代</sectionB><sectionC>影响   废止</sectionC><sectionD>价值   取消</sectionD><answer>B</answer></item><item><itemNumber>2</itemNumber><itemTitle>收藏家从来不是将艺术品作为商品来对待的人，对他们而言，收藏________是一种暂时性的投资，________是一种激情：艺术的激情，物质的激情，历史的激情，占有的激情。正是这种激情重新改写了艺术品的意义。填入划横线部分最恰当的一项是：
</itemTitle><sectionA>与其说      不如说</sectionA><sectionB>不仅          而且</sectionB><sectionC>尽管          然而</sectionC><sectionD>哪怕          也</sectionD><answer>A</answer></item><item><itemNumber>3</itemNumber><itemTitle>一个人拥有包容心态，在为人处事时就不会_______，也不会卑躬屈膝，他会平心静气，拒绝浮华，兼收并蓄，包容万物。
填入划横线部分最恰当的一项是：
</itemTitle><sectionA>目空一切</sectionA><sectionB>盛气凌人</sectionB><sectionC>狂妄自大</sectionC><sectionD>仗势欺人</sectionD><answer>B</answer></item><item><itemNumber>4</itemNumber><itemTitle>关于兰州拉面用“食用胶”使面条筋道的报道，再一次_______了公众对于“食品添加剂”敏感的神经。“吃一碗面等于吃掉一只塑料袋”的恐吓，成功地煽起了公众的_______这再次凸显，我们的记者急需提升基本的科学素养。
填入划横线部分最恰当的一项是：
</itemTitle><sectionA>震动    惊慌</sectionA><sectionB>触动    慌乱</sectionB><sectionC>拨动    恐慌</sectionC><sectionD>惊动    恐惧</sectionD><answer>C</answer></item><item><itemNumber>5</itemNumber><itemTitle>似曾相识的故事，只要你静心观察，就在我们生活周遭日复一日________地演出。人生旅途看起来纷繁纷沓，置身其中才知那是独来独往的终身体验——沿途的浮光掠影响，何尝不是为了成就我们或丰饶或________的内在？填入划横线部分最恰当的一项是：
</itemTitle><sectionA>单一式  单薄</sectionA><sectionB>木偶式  贫穷</sectionB><sectionC>平面化  骨感</sectionC><sectionD>机械化  贫瘠</sectionD><answer>D</answer></item><item><itemNumber>6</itemNumber><itemTitle>下列词语中，没有错别字的一项是
</itemTitle><sectionA>范筹  抉择  棉里藏针  望风披靡</sectionA><sectionB>防害  亟待  徇私枉法  挺而走险</sectionB><sectionC>枯躁  脉络  投鼠忌器  因噎费食</sectionC><sectionD>怂恿  羁绊  阴谋诡计  同仇敌忾</sectionD><answer>D</answer></item><item><itemNumber>7</itemNumber><itemTitle>下列句子中，括号内的成语使用不恰当的一项是：
</itemTitle><sectionA>不到实际中去调查，光靠少数人（苦心孤诣），是解决不了问题的。</sectionA><sectionB>假如每个人都能（见贤思齐），以人之长补已之短，那么我们的生活将变得愈加美好。</sectionB><sectionC>永远不要对他人的苦难（无动于衷），因为谁也无法保证下一个不是你。</sectionC><sectionD>顶尖人才大多不是培养出来的，这是一个（耳顺之年）的老教师最爱讲的话。</sectionD><answer>A</answer></item><item><itemNumber>8</itemNumber><itemTitle>下列句子中，句意明确，没有语病的一项是：
</itemTitle><sectionA>王教授仔细分析了那两套应急方案，反复斟酌后说：“要是如果让我选择的话，我选第一套方案。”</sectionA><sectionB>郭美美事件引发了社会对红十字会如何化解危机、信息透明化的重要性以及商界的社会责任等各方面问题的广泛讨论。</sectionB><sectionC>要是一个共产党员的理想信念不坚定，那么他即使工作能力很强，也不应该被委以重任，因为他迟早会出大问题。</sectionC><sectionD>不同民族对“龙”的认识和联想各不相同，在很大程度上是受地理环境、民情风俗和宗教信仰等因素的影响造成的。</sectionD><answer>B</answer></item><item><itemNumber>9</itemNumber><itemTitle>判断下列句子中使用的修辞手法，不正确的一项是：
</itemTitle><sectionA>墙上芦苇，头重脚轻根底浅；山间竹笋，嘴尖皮厚腹中空。（对偶）</sectionA><sectionB>雷锋说：“大嫂，别问了，我叫解放军，就住在中国。”（借代）</sectionB><sectionC>古老的神州是一头沉睡未醒的睡狮，一旦觉醒，定会横空出世。（比拟）</sectionC><sectionD>燕子去了，有再来的时候，杨柳枯了，有再青的时候；桃花谢了，有再开的时候。（排比）</sectionD><answer>C</answer></item><item><itemNumber>10</itemNumber><itemTitle>①我的食物基本都不是我自己做的，衣服更是一件都没做过。
②用我们的专长来表达是唯一的方式——因为我们不会写鲍勃?迪伦的歌或汤姆?斯托帕德的戏剧。
③我想大多数创造者都想为我们得以利用前人取得的成就表达感激。
④我并没有发明我用的语言或数学。
⑤我们很多人都想回馈社会，在这股洪流中再添上一笔。
⑥我所做的每一件事都有赖于我们人类的其他成员，以及他们的贡献和成就。
将以上6个句子重新排列，语序正确的是：
</itemTitle><sectionA>③⑥①④⑤②</sectionA><sectionB>⑥④③①②⑤</sectionB><sectionC>③④①⑥⑤②</sectionC><sectionD>⑥⑤②①④③</sectionD><answer>C</answer></item><item><itemNumber>11</itemNumber><itemTitle>①这其中一脉相承地贯穿了中国传统山水文化的精神和理念，体现了天人合一的历史文化的延续性。
②主要原因在于历史上的杭州人将传统山水文化的理念和西湖的治理融合在一起，并将这种融合延续下来，两者缺一不可。
③中国拥有湖泊的城市很多，但为什么城市发展与景观和谐并存的鲜而有之，而尤以杭州与西湖这一例凸显了出来？
④这种天人合一的延续性，是中国其他城市普遍缺失的。
⑤我们翻阅西湖的历史，那就是一部保护与治理的历史，就是城市建设与景观建设相辅相成的历史。
将以上5个句子重新排列，语序正确的是：
</itemTitle><sectionA>①④③⑤②</sectionA><sectionB>③⑤④①②</sectionB><sectionC>⑤①④③②</sectionC><sectionD>③②④①⑤</sectionD><answer>C</answer></item><item><itemNumber>12</itemNumber><itemTitle>①他们保存历史的唯一办法是将历史当作传说讲述，由讲述人一代接一代地将史实描述为传奇故事口传下来。
②但是，没有人能把他们当时做的事情记载下来。
③这些传说是很有用的，因为它们能告诉我们以往人们迁居的情况。
④我们从书籍中可以读到5000年前近东发生的事情，那里的人最早学会了写字。
⑤但直到现在，世界上仍然有些地方，人们还不会书写。
将以上5个句子重新排列，语序正确的是：
</itemTitle><sectionA>①③②④⑤</sectionA><sectionB>④①③②⑤</sectionB><sectionC>④⑤①③②</sectionC><sectionD>①②③④⑤</sectionD><answer>C</answer></item><item><itemNumber>13</itemNumber><itemTitle>①虽然在诸多布衣之士那里，把功成身退视为理想的结局，但无可否认，在他们的内心深处，亦有渴望乃至留恋荣华富贵的虚荣感和现世享受的功利观念。
②因为在他们的思想中，出而为仕的主要目的是为了推行他们理想中的道，而荣华富贵是附着于上的次生品。
③渴望遇合，达则兼济天下，救国难，解民困，建不朽之功、永世之业，这是布衣之士共同的理想目标。
④乐道安贫是布衣之士在长时期的历史过程中形成的可贵的精神气节。
⑤然而，在荣华富贵与道之间，布衣之士首先选择的还是道。
⑥当其与道不违时，他们可以而且也乐于接受；反之，就会毫不犹豫地舍弃它。
将以上6个句子重新排列，语序正确的是：
</itemTitle><sectionA>③①④②⑥⑤</sectionA><sectionB>③②⑤④⑥①</sectionB><sectionC>④①⑤⑥②③</sectionC><sectionD>④③①⑤②⑥</sectionD><answer>D</answer></item><item><itemNumber>14</itemNumber><itemTitle>政府的信息发布在定位上应当有所不同。重在体现政务微博的“公共性”。在“卷心菜”事件中，“上海发布”的“公共性”体现为着意搭建城市供应与市民需求之间的关联：要让一个特大城市巨量的市民得到稳定的日常供应保障，不容易；而要让供应市民的蔬菜种植者，在“看天吃饭”生产状态还无法改变的情况下，利益得到保障，从而维持种菜积极性和稳定性，更不容易——________，而不是仅仅关心吃菜市民的便宜、方便，正是“卷心菜”信息发布时的公共定位。填入划横线部分最恰当的一句是：
</itemTitle><sectionA>切实维护好广大种菜农民的利益</sectionA><sectionB>同时着眼生产和消费两方面</sectionB><sectionC>建立起吃菜市民和种菜农民的情感关联</sectionC><sectionD>全面考虑“卷心菜”信息发布的作用</sectionD><answer>B</answer></item><item><itemNumber>15</itemNumber><itemTitle>科学是认识客观世界的动态过程。科学活动特别是现代科学活动，可以根据社会需要、已有知识的指导、前人的经验和学科的预测而设定目标，安排计划。然而，与按既定规程动作的物质生产过程不同，________，因而难以完全按预定的目的和计划进行，有其不确定性和强烈的探索性。
填入划横线部分最恰当的一句是：
</itemTitle><sectionA>科学活动面对的是未知的或知之较少的世界</sectionA><sectionB>科学活动是社会的一种精神生产</sectionB><sectionC>科学活动的具体形式多种多样</sectionC><sectionD>科学活动需要不断创新</sectionD><answer>A</answer></item><item><itemNumber>16</itemNumber><itemTitle>在现代民主制国家中，法律至少在形式上追求六个方面的价值目标，即平等、民主、秩序、自由和效率以及程序的正义，为了实现上述的价值或协调上述价值以充分发挥其调整社会关系的功能和效率，法律必须首先确立其在社会成员中的权威，使人们自愿接受它所确立的行为规范，而要促成这种结果，就一定要依靠民主制度自身的建设，民主愈发达，就愈能有效地控制权力的滥用和特权的滋生。这将成为法律的使用和遵守提供良好的政治环境和社会环境，法律也因此而更加具有权威性和有效性。
这段文字意在说明：
</itemTitle><sectionA>民主是现代法最核心的价值目标</sectionA><sectionB>民主是实现现代法价值的前提和基础</sectionB><sectionC>民主决定现代法的发展方向</sectionC><sectionD>民主是现代法的威力与作用的保障</sectionD><answer>D</answer></item><item><itemNumber>17</itemNumber><itemTitle>文化“必定有异”，文明“难免有异”；文化“必须存异”，文明“可以存异”。这就是文化与文明的区别。所以。文化可以交流，甚至融合，但最终“存异”。文明的趋向，却是“求同”。因为文明的背后，是核心价值；而只有人类的共同价值，才最有价值。由此可见，只要把握了全人类的共同价值，又能兼收并蓄各民族的不同文化，那就能打造出自己的“文化航母”。
根据这段文字，不能得出的观点是：
</itemTitle><sectionA>“求同”是打造文化航母的根本</sectionA><sectionB>文化对“异”的包容程度要宽于文明</sectionB><sectionC>世界文明存在着不同价值取向</sectionC><sectionD>文化即使融合也难以消除差异</sectionD><answer>A</answer></item><item><itemNumber>18</itemNumber><itemTitle>在信仰崩溃的时代，那些佯癫装疯的狂人倒是一些太严肃地对待其信仰的人。鲁迅深知此中之理，说嵇康、阮籍表面上毁坏礼教，实则倒是太相信礼教，因为不满意当权者利用和亵渎礼教，才以反礼教行为发泄内心愤想。其实，在任何信仰体制之下，多数人并非真有信仰，只是做出相信的样子罢了。于是，过分认真的人就起而论究是非，阐释信仰之真谛，结果被视为异端。
对这段文字主要意思概括最恰当的一项：
</itemTitle><sectionA>真正有信仰的人并不多</sectionA><sectionB>真正有信仰者往往是那些被视为异端的人</sectionB><sectionC>把信仰太当回事会使人行为不正常</sectionC><sectionD>很多自称有信仰的人只是徒有其名</sectionD><answer>B</answer></item><item><itemNumber>19</itemNumber><itemTitle>纵然有一百个理由为职业“光环”褪色而辩解，更有一万个理由要求这个职业不能踩踏底线、弃守底线，不管是搬出为了生存的经济理由，还会将良知的确实归咎为体制的束缚，将一切推责给外部的环境，都是对职业；伦理的残害。
这段文字意在说明
</itemTitle><sectionA>体制的束缚是职业；伦理的主因</sectionA><sectionB>体制伦理受损一般源于职业“光环”的褪色</sectionB><sectionC>任何时候都不能突破职业道德底线</sectionC><sectionD>弃守底线者总会给自己找借口</sectionD><answer>C</answer></item><item><itemNumber>20</itemNumber><itemTitle>在几千年的历史中，我们始终没有断过敌人，东南西北，四面都有。虽然有的当年的敌人今天可能已融入中华民族之中；但是在当年他们只能算是敌人。我们决不能把古代史现代化，否则我们的苏武、岳飞、文天祥等一大批著名的爱国者，就都被剥去了爱国的光环，成为内战的牺牲者。
这段文字的主旨是：
</itemTitle><sectionA>民族英雄都是爱国者</sectionA><sectionB>内战和统一的交替是历史发展的规律</sectionB><sectionC>不同时期的爱国主义都具有狭隘性</sectionC><sectionD>不能因历史变迁而否定民族英雄事迹</sectionD><answer>D</answer></item><item><itemNumber>21</itemNumber><itemTitle>现代的学术发言环境比过去很多了，可知识分子中存在一种奇怪的犬儒主义，不敢把自己的思想讲出啦，唯恐得罪什么人。之所以存在这种情况，有些是过去搞怕了，有些是胆小，但你在学术界，不把真正的问题讲出来，看脸色行事，是做不成学问、搞不成研究的。
对这段文字的主要意思概括最恰当的一项是：
</itemTitle><sectionA>做学问要敢于挑战权威</sectionA><sectionB>没有骨气的人成不了学术大家</sectionB><sectionC>敢于表达自己的思想才能做好学问</sectionC><sectionD>学术环境是影响学术成就的重要因素</sectionD><answer>C</answer></item><item><itemNumber>22</itemNumber><itemTitle>第二次世界大战后，多数先行国家的行政重心逐渐向社会福利管理转移，它们的人口基础管理，普遍形成了一种以“人口服务”为主的新体制。这种体制并没有放弃人口的管控，知识这种管控核心目标是人口服务，基本手段是人口服务，表现形式也是人口服务。它将管控寓于服务之中，而不是相反。我国社会转型下的人口管理，显然也面临着类似的调整。
以下表述与这段文字意思不相符的是：
</itemTitle><sectionA>我国的人口管理应确立人口服务的管理宗旨</sectionA><sectionB>人口管控与人口服务是完全不同的两种模式</sectionB><sectionC>先行国家的人口管理转型是行政重心转移的结果</sectionC><sectionD>人口管理的新体制通过人口服务实现人口管控</sectionD><answer>B</answer></item><item><itemNumber>23</itemNumber><itemTitle>世界是由无数具体事务及其联系构成的有机整体。按照认识的顺序，人民的认识是从具体的、个别的、有限的事务开始，然而人的思维本性总是不满足于对具体事务的个别方面或局部的支离破碎的认识，不愿意停留在“管中窥豹只见一斑”的状态。人民孜孜不倦地探索诸多看似孤立的实物背后的内在联系，苦苦寻找那种把自然界、人类社会和人的将身世界统一起来并起支配作用这种形而上的思考就是哲学思考，自古至今，从未中断。
对这段文字的主要意思概括最恰当的一项是：
</itemTitle><sectionA>哲学思考追求整体性</sectionA><sectionB>哲学思考意在揭示事物的本质</sectionB><sectionC>哲学思考具有连续性</sectionC><sectionD>哲学思考以抽象思维为主导</sectionD><answer>B</answer></item><item><itemNumber>24</itemNumber><itemTitle>在中国文化的剧烈冲击下，佛教如果不能适应现实情况，必然不能在中国立定脚跟，于是佛教只能趉某一些伪装，以求得生存。早起佛典中有些地方特别强调“孝”字，就是歪曲原文含义以适应中国具有浓厚纲纪色彩文化的要求。
对这段文字的主要意思概括最恰当的一项是：
</itemTitle><sectionA>佛教是一个适应性很强的宗教</sectionA><sectionB>“孝”是佛典发展过程中衍生出来的要义之一</sectionB><sectionC>佛学在中国传统文化传承中的英雄较深</sectionC><sectionD>传统文化的力量迫使佛教在传播中采取了变通策略</sectionD><answer>D</answer></item><item><itemNumber>25</itemNumber><itemTitle>君子所见无不善，小人所见无不恶。拾荒的陈阿姨并不像一些人那样，将帮助别人这种再简单不过的事情也想象的那样复杂、可怕。作为一个真正富有正义感的人，不会在助人为乐之前就考虑自己做了好事是不是会被冤枉，为自己寻找一个不作为的借口。举手之劳怎么却变得如此艰难，要不要扶起倒地的弱者似乎成了今天一个重要的社会问题。
这段文字意在说明：
</itemTitle><sectionA>要积极营造助人为乐的社会环境</sectionA><sectionB>有正义感的人做好事时不会考虑得失</sectionB><sectionC>遇到弱者需要帮助时，我们应伸出援助之手</sectionC><sectionD>当今社会缺乏正义感，出现了道德危机</sectionD><answer>D</answer></item><item><itemNumber>26</itemNumber><itemTitle>在深刻变化的社会转向期，思想观念多样多元多变，一些领域道德______，一些社会成员人生观、价值观扭曲，这是文艺工作者必须面对的时代_______；如何实现文艺的社会价值，净化心灵，烛照前行，这是文艺工作者必须回答的时代_______。
填入话横线部分最恰当的一项是：
</itemTitle><sectionA>失当   背景  主题</sectionA><sectionB>缺失  环境  议题</sectionB><sectionC>失范  场景  命题</sectionC><sectionD>缺乏  境况  问题</sectionD><answer>C</answer></item><item><itemNumber>27</itemNumber><itemTitle>这首______的山西民歌，将男女之爱，离情别绪与人生苦情一并抒发，以凄婉的歌声，揭开了移民史上________的一页，饱含着时代的沧桑
填入划横线部分最恰当的一项是：
</itemTitle><sectionA>脍炙人口   波澜壮阔</sectionA><sectionB>脍炙人口  气势磅礴</sectionB><sectionC>喜闻乐见  浩浩荡荡</sectionC><sectionD>喜闻乐见  沧海桑田</sectionD><answer>A</answer></item><item><itemNumber>28</itemNumber><itemTitle>领导人下台只是欧债危机的一个后果，并非医治危机的；良药。欧洲依然在艰难_______，并试图寻求外界的援助，但是大西洋对岸的美国盟友已经_______，有实力施以援手的是在欧亚大陆另一端的中国。
填入划横线部分最恰当的一项是：
</itemTitle><sectionA>挣扎  形影相吊</sectionA><sectionB>踟蹰  焦头烂额</sectionB><sectionC>突围  自顾不暇</sectionC><sectionD>徘徊  分身乏术</sectionD><answer>C</answer></item><item><itemNumber>29</itemNumber><itemTitle>亚当·斯密认为，人们只有享有参与到市场经济进程的_____，才会增加财富。只有在这样的背景下，人们才能寻找到他得比较优势，才能_____每个人身上的企业家禀赋。因此有人说，其实每个人都是企业家，每个人都在创新，_____是我们的制度设计是否给每个人这样的机会。
 填入画横线部分最恰当的一项是：
</itemTitle><sectionA>自由   激活   关键</sectionA><sectionB>保障    引发   前提</sectionB><sectionC>权利   驱动   主要</sectionC><sectionD>保证    释放   条件</sectionD><answer>A</answer></item><item><itemNumber>30</itemNumber><itemTitle>有的人藐视一切他们弄不懂的事物，以______来掩盖自己的______。
填入划横线部分最恰当的一项是：
</itemTitle><sectionA>无畏  平庸</sectionA><sectionB>愚昧  自负</sectionB><sectionC>轻蔑  无知</sectionC><sectionD>不屑  自卑</sectionD><answer>C</answer></item><item><itemNumber>31</itemNumber><itemTitle>革命免不了使用暴力，免不了造成社会一定的破坏和震荡，这是_____的客观事实。有人据此否定了革命，认为革命的代价太大，不如采取和平渐进的改良方式为好，这种观点貌似有理，但它脱离具体情况抽象地议论改良和革命孰优孰劣，实则毫无意义。
  填入画横线部分最恰当的一项是：
</itemTitle><sectionA>不可否认</sectionA><sectionB>毋庸置疑</sectionB><sectionC>不言而喻</sectionC><sectionD>无可争辩</sectionD><answer>B</answer></item><item><itemNumber>32</itemNumber><itemTitle>我国传统法律文化中确实存在大量与现代法治______的消极因素，它们严重阻碍了法律文化传统的自我更新，但同时，我们不能因为就简单否定其全部价值，毕竟，“传统是历史和文化的积淀，只能更新，不能铲除，失去传统就失去了民族文化的特点，就失去了前进的历史与文化的基础”。
填入划横线部分最恰当的一项是：
</itemTitle><sectionA>大相径庭</sectionA><sectionB>扞格不入</sectionB><sectionC>背道而驰</sectionC><sectionD>截然不同</sectionD><answer>B</answer></item><item><itemNumber>33</itemNumber><itemTitle>有人总是把工作当成一种负担，得过且过，搪塞敷衍，这是很可怕的，因为慢慢地你的理想就会被_______，志气就会被吞食，最终难免迷失方向，沦为平庸之辈。
填入划横线部分最恰当的一项是：
</itemTitle><sectionA>磨灭</sectionA><sectionB>摧毁</sectionB><sectionC>丢弃</sectionC><sectionD>消磨</sectionD><answer>A</answer></item><item><itemNumber>34</itemNumber><itemTitle>扬善必须抑恶，扶正自应祛邪，一个健康文明的社会当然不应让横行一方为非作歹的黑恶势力逍遥法外，不应为毒害健康_____暴利的无良企业庇护，不应对权钱勾结贪婪摄取的腐败现象_______，不应让_______侵夺他人权益的缺德行为无所制约。
填入划横线部分最恰当的一项是：
</itemTitle><sectionA>获取  漠然置之  随意</sectionA><sectionB>获取  不闻不问  恣意</sectionB><sectionC>牟取  置之不理  任意</sectionC><sectionD>牟取  麻木不仁  肆意</sectionD><answer>D</answer></item><item><itemNumber>35</itemNumber><itemTitle>下列词语中，加点字读音不正确的一项是：
</itemTitle><sectionA>湍（tuān）急</sectionA><sectionB>谲（jué）诈</sectionB><sectionC>木讷（nè）</sectionC><sectionD>牛虻（máng）</sectionD><answer>D</answer></item><item><itemNumber>36</itemNumber><itemTitle>2，4，3，7，16，107，（    ）
</itemTitle><sectionA>1594</sectionA><sectionB>1684</sectionB><sectionC>1707</sectionC><sectionD>1856</sectionD><answer>C</answer></item><item><itemNumber>37</itemNumber><itemTitle>243，162，108，72，48，（    ）
</itemTitle><sectionA>26</sectionA><sectionB>28</sectionB><sectionC>30</sectionC><sectionD>32</sectionD><answer>D</answer></item><item><itemNumber>38</itemNumber><itemTitle>3，-2，1，3，8，61，（    ）
</itemTitle><sectionA>3692</sectionA><sectionB>3713</sectionB><sectionC>3764</sectionC><sectionD>3816</sectionD><answer>B</answer></item><item><itemNumber>39</itemNumber><itemTitle>1，6，5，7，2，8，6，9，（    ）
</itemTitle><sectionA>1</sectionA><sectionB>2</sectionB><sectionC>3</sectionC><sectionD>4</sectionD><answer>C</answer></item><item><itemNumber>40</itemNumber><itemTitle>四个连续奇数的和为32，则它们的积为多少？
</itemTitle><sectionA>945</sectionA><sectionB>1875</sectionB><sectionC>2745</sectionC><sectionD>3465</sectionD><answer>D</answer></item><item><itemNumber>41</itemNumber><itemTitle>某班级去超市采购体育用品时发现买4个篮球和2个排球共需560元，而买2个排球和4个足球则共需500元。问如果篮球、排球和足球各买1个，共需多少元？
</itemTitle><sectionA>250元</sectionA><sectionB>255元</sectionB><sectionC>260元</sectionC><sectionD>265元</sectionD><answer>D</answer></item><item><itemNumber>42</itemNumber><itemTitle>有一个长方体容器，长40厘米，宽30厘米，高10厘米，里面的水深6厘米（最大面为底面）。如果把这个容器盖紧，再竖起来（最小面为底面），里面的水深是多少厘米？
</itemTitle><sectionA>15厘米</sectionA><sectionB>18厘米</sectionB><sectionC>24厘米</sectionC><sectionD>30厘米</sectionD><answer>C</answer></item><item><itemNumber>43</itemNumber><itemTitle>一容器内有浓度为30%的糖水，若再加入30千克水与6千克糖，则糖水的浓度变为25%。问原来糖水中含糖多少千克？
</itemTitle><sectionA>15千克</sectionA><sectionB>18千克</sectionB><sectionC>21千克</sectionC><sectionD>24千克</sectionD><answer>B</answer></item><item><itemNumber>44</itemNumber><itemTitle>A、B两地间有条公路，甲、乙两人分别从A、B两地出发相向而行，甲先走半小时后，乙才出发，一小时后两人相遇，甲的速度是乙的2/3。问甲、乙所走的路程之比是多少？
</itemTitle><sectionA>5∶6</sectionA><sectionB>1∶1</sectionB><sectionC>6∶5</sectionC><sectionD>4∶3</sectionD><answer>B</answer></item><item><itemNumber>45</itemNumber><itemTitle>南阳中学有语文教师8名，数学教师7名、英语教师5名和体育教师2名。现要从以上四科教师中各选出1名教师去参加培训，问共有几种不同的选法？
</itemTitle><sectionA>96种</sectionA><sectionB>124种</sectionB><sectionC>382种</sectionC><sectionD>560种</sectionD><answer>D</answer></item><item><itemNumber>46</itemNumber><itemTitle>有一个上世纪80年代出生的人，如果他能活到80岁，那么有一年他的年龄的平方数正好等于那一年的年份。问此人生于哪一年?
</itemTitle><sectionA>1980年</sectionA><sectionB>1983年</sectionB><sectionC>1986年</sectionC><sectionD>1989年</sectionD><answer>A</answer></item><item><itemNumber>47</itemNumber><itemTitle>有编号为1-13的卡片，每个编号有4张，共有52张卡片。问至少摸出多少张，就可保证一定有3张卡片编号相连？
</itemTitle><sectionA>27张</sectionA><sectionB>29张</sectionB><sectionC>33张</sectionC><sectionD>37张</sectionD><answer>D</answer></item><item><itemNumber>48</itemNumber><itemTitle>某演唱会检票前若干分钟就有关注开始排队等候入场，而每分钟来的观众人数一样多。从开始检票到等候队伍消失，若同时开4个入场口需50分钟，若同时开6个入场口则需30分钟。问如果同时开7个入场口需几分钟？
</itemTitle><sectionA>18分钟</sectionA><sectionB>20分钟</sectionB><sectionC>22分钟</sectionC><sectionD>25分钟</sectionD><answer>D</answer></item><item><itemNumber>49</itemNumber><itemTitle>一个班里有30名学生，有12人会跳拉丁舞，有8人会跳肚皮舞，有10人会跳芭蕾舞。问至多几人回跳两种舞蹈？
</itemTitle><sectionA>12人</sectionA><sectionB>14人</sectionB><sectionC>15人</sectionC><sectionD>16人</sectionD><answer>C</answer></item><item><itemNumber>50</itemNumber><itemTitle>有一架天平，只有5克和30克的砝码各一个。现在要用这架天平把300克味精平均分成3份，那么至少需要称多少次？
</itemTitle><sectionA>3次</sectionA><sectionB>4次</sectionB><sectionC>5次</sectionC><sectionD>6次</sectionD><answer>A</answer></item><item><itemNumber>51</itemNumber><itemTitle>眼睛：虹膜
</itemTitle><sectionA>骨头：关节</sectionA><sectionB>乔木：白桦</sectionB><sectionC>衣服：丝绸</sectionC><sectionD>手表：表带</sectionD><answer>D</answer></item><item><itemNumber>52</itemNumber><itemTitle>蝴蝶：蟋蟀
</itemTitle><sectionA>桑椹：鲜花</sectionA><sectionB>海棠：海参</sectionB><sectionC>鹦鹉：海鸥</sectionC><sectionD>恒星：太阳</sectionD><answer>C</answer></item><item><itemNumber>53</itemNumber><itemTitle>土地：农民
</itemTitle><sectionA>资本：商人</sectionA><sectionB>药方：医生</sectionB><sectionC>晚会：歌手</sectionC><sectionD>课本：教师</sectionD><answer>A</answer></item><item><itemNumber>54</itemNumber><itemTitle>创造：历史
</itemTitle><sectionA>发展：经济</sectionA><sectionB>和谐：社会</sectionB><sectionC>发扬：光大</sectionC><sectionD>生产：积累</sectionD><answer>A</answer></item><item><itemNumber>55</itemNumber><itemTitle>票友：业余
</itemTitle><sectionA>专家：肤浅</sectionA><sectionB>运动员：瘦弱</sectionB><sectionC>教师：慈祥</sectionC><sectionD>艺术大师：著名</sectionD><answer>D</answer></item><item><itemNumber>56</itemNumber><itemTitle>出人头地：苏轼
</itemTitle><sectionA>东山再起：谢安</sectionA><sectionB>多多益善：项羽</sectionB><sectionC>投笔从戎：班固</sectionC><sectionD>指鹿为马：李林甫</sectionD><answer>A</answer></item><item><itemNumber>57</itemNumber><itemTitle>百发百中：百步穿杨
</itemTitle><sectionA>门可罗雀：班门弄斧</sectionA><sectionB>深思熟虑：优柔寡断</sectionB><sectionC>不求甚解：囫囵吞枣</sectionC><sectionD>白日做梦：梦想成真</sectionD><answer>C</answer></item><item><itemNumber>58</itemNumber><itemTitle>道德：行为：约束
</itemTitle><sectionA>权力：人民：服务</sectionA><sectionB>信仰：图腾：崇拜</sectionB><sectionC>教师：教育：学生</sectionC><sectionD>法律：犯罪：惩治</sectionD><answer>D</answer></item><item><itemNumber>59</itemNumber><itemTitle>煤气灶：主妇：做饭
</itemTitle><sectionA>车间：工程师：生产</sectionA><sectionB>炼丹：道士：修行</sectionB><sectionC>剪刀：理发师：美发</sectionC><sectionD>马路：清洁工：打扫</sectionD><answer>C</answer></item><item><itemNumber>60</itemNumber><itemTitle>微博：媒体：消息
</itemTitle><sectionA>股票：有价证劵： 金融</sectionA><sectionB>护照：证件：身份</sectionB><sectionC>长城：景点：北京</sectionC><sectionD>债权：权利：债务</sectionD><answer>B</answer></item><item><itemNumber>61</itemNumber><itemTitle>附条件的民事法律行为：在意思表示当中附有决定该行为效力发生或者消灭条件的民事法律行为。
下列哪一项属于附条件的民事法律行为？
</itemTitle><sectionA>甲、乙订立房屋租赁合同，约定出租人甲的儿子一旦结婚需要布置新房时，就终止合同。</sectionA><sectionB>甲对乙说：“如果我儿子考上名牌大学，我一定请你吃饭。”</sectionB><sectionC>甲与乙签订夏粮买卖合同，约定11月中旬生效。</sectionC><sectionD>甲与乙约定：如果甲晚上帮乙一起去打乙的仇人，乙就付给甲1000元钱。</sectionD><answer>A</answer></item><item><itemNumber>62</itemNumber><itemTitle>行政成本：政府为了社会的公共管理和为公众提供公共服务付出的代价，包括直接行政成本和间接行政成本。
下列没有涉及行政成本的一项是：
</itemTitle><sectionA>某政府部门为了提高工作效率合并机构、精简工作人员。</sectionA><sectionB>某区政府为应对私家车增多的问题，新建了两个地下公共停车场。</sectionB><sectionC>某商业银行为方便广大用户处理业务，耗费巨资开通了手机银行业务。</sectionC><sectionD>某公安局招聘交通协管员协助交警维护交通秩序。</sectionD><answer>C</answer></item><item><itemNumber>63</itemNumber><itemTitle>无因管理：没有法律规定或者约定的义务而为他人管理事务。
下列行为中不属于无因管理的一项是：
</itemTitle><sectionA>甲收留了一位迷路的儿童，一边让他在自己家吃住，一边四处打听儿童父母的住址。</sectionA><sectionB>甲失踪后，其财产代管人乙对甲的财产进行管理。</sectionB><sectionC>甲看见有几个人在殴打乙，立即上前制止。</sectionC><sectionD>甲的邻居乙家失火，甲怕火烧伤乙家的小孩，于是实施救火。</sectionD><answer>B</answer></item><item><itemNumber>64</itemNumber><itemTitle>简单命题：不包含其他命题的命题，只能把它分析为不同的词项，不能再把它分析为其他命题，因此又叫作“原子命题”。
下列哪项不是简单命题？
</itemTitle><sectionA>小明和小红是朋友。</sectionA><sectionB>生命在于运动。</sectionB><sectionC>掷骰子4点朝上的概率是1/6</sectionC><sectionD>小张既高且胖。</sectionD><answer>D</answer></item><item><itemNumber>65</itemNumber><itemTitle>角色冲突：当一个人扮演一个角色或同时扮演几个不同角色时，由于不能胜任，造成不合适宜而发生的矛盾和冲突。
下列情形中不属于角色冲突的一项是：
</itemTitle><sectionA>一些大一新生入学后，面对新的生活环境很不适应。</sectionA><sectionB>某公司一职员由于业绩出众，被公司提拔为销售经理，但是他感到力不从心。</sectionB><sectionC>假期里，张某的妻子想让他陪她出去旅游，而他母亲想让他回家陪陪父母。</sectionC><sectionD>在边远山区的一所小学里，某位老师既教数学，又教语文，但学生们的两门功课成绩都很好。</sectionD><answer>D</answer></item><item><itemNumber>66</itemNumber><itemTitle>不可能所有深圳人都很有钱。”以下哪项断定的涵义，与上述断定最为接近?
</itemTitle><sectionA>可能有的深圳人不是很有钱</sectionA><sectionB>可能有的深圳人很有钱</sectionB><sectionC>必然有的深圳人不是很有钱</sectionC><sectionD>必然大部分深圳人都很有钱</sectionD><answer>C</answer></item><item><itemNumber>67</itemNumber><itemTitle>“小孙并非既会游泳又会打网球。”根据以上描述，下列哪项断定必然为真？
</itemTitle><sectionA>如果小孙不会打网球，那么他一定会游泳</sectionA><sectionB>如果小孙会打网球，那么他一定不会游泳</sectionB><sectionC>小孙既不会游泳，也不会打网球</sectionC><sectionD>小孙会游泳，但不会打网球</sectionD><answer>B</answer></item><item><itemNumber>68</itemNumber><itemTitle>以“如果孙强、李超不是优秀共青团员，那么周红是优秀共青团员”为一前提，若要必然推出“李超是优秀共青团员”，则需要下列哪项作为前提？
</itemTitle><sectionA>周红不是优秀共青团员</sectionA><sectionB>孙强是优秀共青团员</sectionB><sectionC>周红是优秀共青团员，而孙强不是优秀共青团员</sectionC><sectionD>孙强和周红都不是优秀共青团员</sectionD><answer>D</answer></item><item><itemNumber>69</itemNumber><itemTitle>暑假里，小张的父母给小张报了摄影兴趣班和美术兴趣班。小张知道后说，以后我又不想成为摄影家，何必学摄影。以下哪项是小张的回答中包含的前提?
</itemTitle><sectionA>学摄影的不一定能成为摄影家</sectionA><sectionB>小张更想成为一名画家，而不是摄影家</sectionB><sectionC>只有想成为摄影家，才需要学摄影</sectionC><sectionD>与摄影相比，小张更喜欢学画画</sectionD><answer>C</answer></item><item><itemNumber>70</itemNumber><itemTitle>某大学寝室有8个人，三个是广东人，一个是北京人，有两个是北方人，一个是保送生，三个是贫困生。假设上述介绍涉及该寝室的所有同学，则下列关于该寝室同学的判断与题干有矛盾的是：
</itemTitle><sectionA>保送的学生来自北方</sectionA><sectionB>北京人既不是保送生也不是贫困生</sectionB><sectionC>有两个贫困生是广东人</sectionC><sectionD>没有一个来自黑龙江的学生</sectionD><answer>C</answer></item><item><itemNumber>71</itemNumber><itemTitle>宏达公司管理人员的平均年薪为20万元，而销售人员的平均年薪是18万元，公司的所有员工的平均年薪是12万元。如果以上信息是正确的，能够推出以下哪一项结论？
</itemTitle><sectionA>至少有一位员工的年薪比销售人员的平均年薪低</sectionA><sectionB>没有一位销售人员的年薪比管理人员高</sectionB><sectionC>至少有一半管理人员的年薪比销售人员的平均年薪高</sectionC><sectionD>宏达公司的管理人员少于销售人员</sectionD><answer>A</answer></item><item><itemNumber>72</itemNumber><itemTitle>如果一个人在A城市乱扔垃圾就会被认为没有道德；一个人如果没有道德，A城市里就没有人和他做朋友；一个人如果在A城市没有朋友就寸步难行，无法继续留在这里。
从上述叙述中，可以推出以下哪项结论？
</itemTitle><sectionA>一个人在B城市乱扔垃圾但是可以留在A城市</sectionA><sectionB>如果一个人道德修养很高，那么他就能留在A城市</sectionB><sectionC>生活在A城市的小李在过马路时将西瓜皮扔在地上，那么他将难以再留在A城市</sectionC><sectionD>小王没有留在A城市说明他缺乏道德修养</sectionD><answer>C</answer></item><item><itemNumber>73</itemNumber><itemTitle>北方某地区为了应对干旱，居民用水量已经受到严重限制。不过，目前水库蓄水量与5年前该地区干旱期的蓄水量持平。既然当年居民生活用水量并未受到限制，所以
现在也不应该受到限制。下列哪一项陈述为真，将最严重地削弱作者的主张？
</itemTitle><sectionA>居民用水量占总用水量的比重很大</sectionA><sectionB>自上次干旱以来，当地政府采取了一些节水措施</sectionB><sectionC>5年来该地区的人口数量显著增加</sectionC><sectionD>自上次干旱以来，该地区并没有建造新的水库</sectionD><answer>C</answer></item><item><itemNumber>74</itemNumber><itemTitle>科学家研究发现，由能承担部分母亲角色的机器替代母亲“养育”的雌性大猩猩幼崽，当它们有后代时，难以承担母亲的角色。而人类与大猩猩具有很大的相似性，所以婴儿不应该由保姆或日托中心来管，而只应该由他们的亲生母亲来抚育。
下列哪个陈述为真，最能加强作者的结论？
</itemTitle><sectionA>研究表明大猩猩的个体差异不显著</sectionA><sectionB>当由机器替代母亲“养育”长大的雌性大猩猩有后代时，可以教会它们抚育技能</sectionB><sectionC>即使由亲生母亲抚育较短一段时间的大猩猩幼崽，长大后也能承担母亲的角色</sectionC><sectionD>由亲生母亲之外的其他雌性大猩猩抚育的大猩猩幼崽，当它们有后代时，都不能承担母亲的角色</sectionD><answer>D</answer></item><item><itemNumber>75</itemNumber><itemTitle>甲、乙、丙、丁、戊、己是一个家族的兄弟姐妹，已知：甲是男孩，有3个姐姐；乙有一个哥哥和弟弟；丙是女孩，有一个姐姐和一个妹妹；丁的年龄在所有人当中是最大的；戊是女孩，但是她没有妹妹；己既没有弟弟也没有妹妹。
从上述叙述中，可以推出以下哪项结论？
</itemTitle><sectionA>己是女的且年龄最小</sectionA><sectionB>丁是女的</sectionB><sectionC>六个兄弟姐妹中女孩的数量多于男孩的数量</sectionC><sectionD>甲在六个兄弟姐妹中排行第三</sectionD><answer>B</answer></item><item><itemNumber>76</itemNumber><itemTitle>马克思主义哲学认为，认识一旦形成，就会反作用于实践，指导实践的全过程。这是因为：
①实践是检验认识正确与否的唯一标准
②实践目标的确立，需要认识的指导
③对实践手段、方法、道路、步骤的取舍，需要认识的指导
④对实践结果的评价，需要认识的指导
⑤认识在不断发展过程中，需要实践提供动力
</itemTitle><sectionA>①③⑤</sectionA><sectionB>②③④</sectionB><sectionC>①②③④</sectionC><sectionD>②③④⑤</sectionD><answer>B</answer></item><item><itemNumber>77</itemNumber><itemTitle>辛亥革命后屡遭挫折的孙中山先生，把中国共产党人当成亲密朋友，毅然改组国民党，实行三大政策。
</itemTitle><sectionA>联美、溶共、扶助农工</sectionA><sectionB>联俄、联共、扶助农工</sectionB><sectionC>民族、民权、民生</sectionC><sectionD>民族、民主、民生</sectionD><answer>B</answer></item><item><itemNumber>78</itemNumber><itemTitle>在毛泽东思想形成和发展的过程中，毛泽东同志发表过很多著名的文章，以下四篇文章中发表最早的是：
</itemTitle><sectionA>《矛盾论》</sectionA><sectionB>《论持久战》</sectionB><sectionC>《中国社会各阶级的分析》</sectionC><sectionD>《星星之火，可以燎原》</sectionD><answer>C</answer></item><item><itemNumber>79</itemNumber><itemTitle>1992年初，邓小平在南方谈话中提出了判断改革和各方面工作是非得失的“三个有利于”标准，是指是否有利于发展社会主义社会的生产力和_______。
</itemTitle><sectionA>是否有利于增强社会主义国家的综合国力，是否有利于提高人民生活水平</sectionA><sectionB>是否有利于提高人民的生活水平，是否有利于巩固中国共产党的执政地位</sectionB><sectionC>是否有利于增强社会主义国家的国际影响力，是否有利于提高人民的生活水平</sectionC><sectionD>是否有利于发展社会主义社会民主政治，是否有利于发展社会主义先进文化</sectionD><answer>A</answer></item><item><itemNumber>80</itemNumber><itemTitle>“金砖四国”（BRIC）引用了巴西、俄罗斯、印度和中国的首字母。由于该词与英语单词的砖（Brick）类似，因此被称为“金砖四国”。后来哪个国家加入，“金砖四国”的英语单词变为“BRICS”，并改称为“金砖国家”。
</itemTitle><sectionA>沙特阿拉伯</sectionA><sectionB>苏丹</sectionB><sectionC>南非</sectionC><sectionD>西班牙</sectionD><answer>C</answer></item><item><itemNumber>81</itemNumber><itemTitle>2011年12月举行的中央经济工作会议认为，推动2012年经济社会发展，要突出把握好的工作总基调。
</itemTitle><sectionA>调整结构</sectionA><sectionB>加速转型</sectionB><sectionC>稳中求进</sectionC><sectionD>平稳较快发展</sectionD><answer>C</answer></item><item><itemNumber>82</itemNumber><itemTitle>以下哪项最不可能是政府实施最低价控制的原因？
</itemTitle><sectionA>避免价格上的恶性竞争</sectionA><sectionB>保护某行业的收入</sectionB><sectionC>避免某些商品出现短缺</sectionC><sectionD>防止垄断行业索取高额利润</sectionD><answer>D</answer></item><item><itemNumber>83</itemNumber><itemTitle>指出：在一个家庭或在一个国家中，食物支出在收入中所占的比例随着收入的增加而减少。
</itemTitle><sectionA>恩格尔定律</sectionA><sectionB>科斯定理</sectionB><sectionC>凯恩斯主义</sectionC><sectionD>相对收入消费理论</sectionD><answer>A</answer></item><item><itemNumber>84</itemNumber><itemTitle>根据我国宪法规定，下列哪项权利属于公民的基本权利中的政治权利和自由？
</itemTitle><sectionA>平等权</sectionA><sectionB>言论自由</sectionB><sectionC>宗教信仰自由</sectionC><sectionD>批评、建议和检举权</sectionD><answer>B</answer></item><item><itemNumber>85</itemNumber><itemTitle>下列选项中，哪一行为构成正当防卫？
</itemTitle><sectionA>甲到商场购物时将自己的汽车停在商场门口，买完东西出来时发现乙打碎了车窗玻璃，在偷车内的东西，于是上前将乙抓住，并趁乙不注意将其打晕，送往派出所。</sectionA><sectionB>甲持枪闯进某单位财务室，逼着财务室工作人员乙打开保险柜，在甲让乙往口袋里装钱时，乙的同事进来趁甲不注意将其砸成重伤。</sectionB><sectionC>甲对乙心存怨恨，故意辱骂乙，乙气急要动手打甲，甲拿起准备好的棍子将乙手臂打伤</sectionC><sectionD>甲在大街上打电话，被乙抢走了手机，甲追赶乙未果。第二天甲在大街上发现了乙，于是偷偷在其背后将其打倒，抢走了乙身上的财物。</sectionD><answer>B</answer></item><item><itemNumber>86</itemNumber><itemTitle>行政诉讼的一审程序由起诉、受理、审理和裁判四个相互衔接的阶段构成，以下关于该四个阶段的相关表述中，不正确的一项是：
</itemTitle><sectionA>原告起诉，应当有明确的被告和具体的诉讼请求</sectionA><sectionB>人民法院对起诉作审查后，认为符合行政诉讼的受理条件的，应在7日内立案受理</sectionB><sectionC>行政诉讼一审审理的方式为书面审理</sectionC><sectionD>经审理，人民法院认为行政处罚显失公正的，可以判决变更</sectionD><answer>C</answer></item><item><itemNumber>87</itemNumber><itemTitle>根据我国公务员制度的相关规定，录用担及（  ）及其他相当职务层次的非领导职务公务员，采取公开考试、严格考察、平等竞争、择优录取的办法。
</itemTitle><sectionA>科员以上</sectionA><sectionB>主任科员以上</sectionB><sectionC>科员以下</sectionC><sectionD>主任科员以下</sectionD><answer>D</answer></item><item><itemNumber>88</itemNumber><itemTitle>以下是中国一位帝王改革的内容：（1）推行均田制（2）迁都洛阳（3）革除鲜卑旧俗，接受汉族先进文化（4）改革官制，严惩贪污……问这位皇帝是谁？
</itemTitle><sectionA>北魏孝文帝拓跋宏</sectionA><sectionB>辽太祖耶律阿保机</sectionB><sectionC>元太祖铁木真</sectionC><sectionD>金太祖完颜阿骨打</sectionD><answer>A</answer></item><item><itemNumber>89</itemNumber><itemTitle>下列哪一战役是第二次世界大战的转折点，使德国法西斯军队被迫转入战略防御？
</itemTitle><sectionA>不列颠之战</sectionA><sectionB>莫斯科保卫战</sectionB><sectionC>斯大林格勒保卫战</sectionC><sectionD>空袭珍珠港</sectionD><answer>C</answer></item><item><itemNumber>90</itemNumber><itemTitle>下列关于我国国情的表述中，不正确的一项是：
</itemTitle><sectionA>计划生育是我国的基本国策</sectionA><sectionB>民兵是我国武装；力量的组成部分</sectionB><sectionC>我国的耕地面积不足陆地面积的5%</sectionC><sectionD>根据全国第六次人口普查，我国的人口已达13.39亿</sectionD><answer>C</answer></item><item><itemNumber>91</itemNumber><itemTitle>人类科技发展的历程中，先后出现了下列科技词语：①电子计算机②量子力学③航天器④转基因水稻。按时间先后顺序排列正确的是：
</itemTitle><sectionA>①②③④</sectionA><sectionB>②①③④</sectionB><sectionC>②③④①</sectionC><sectionD>③①②④</sectionD><answer>B</answer></item><item><itemNumber>92</itemNumber><itemTitle>下列关于公文知识的表述汇总，不正确的一项：
</itemTitle><sectionA>附件即附注，是公文正文的重要组成部分</sectionA><sectionB>请示应当一文一事，一般只写一个主送机关</sectionB><sectionC>不具隶属相关之间相互商洽工作、询问和答复问题可以用函</sectionC><sectionD>保密公文的密级分为绝密、机密和秘密三种</sectionD><answer>A</answer></item><item><itemNumber>93</itemNumber><itemTitle>下列四个节日中，杭州市白昼最长的是：
</itemTitle><sectionA>元旦</sectionA><sectionB>劳动节</sectionB><sectionC>儿童节</sectionC><sectionD>国庆节</sectionD><answer>C</answer></item><item><itemNumber>94</itemNumber><itemTitle>下列名言与作者的对应关系不正确的一项是：
</itemTitle><sectionA>“朝闻道，夕死可矣。”——孔子</sectionA><sectionB>“生于忧患，死于安乐。”——孟子</sectionB><sectionC>“天行有常，不以尧存，不以桀亡”——荀子</sectionC><sectionD>“兼相爱，交相利。”——老子</sectionD><answer>D</answer></item><item><itemNumber>95</itemNumber><itemTitle>下列有关书画知识的说法中，不正确的是：
</itemTitle><sectionA>“书圣”指王羲之，其代表作《兰亭序》被称为“天下第一行书”</sectionA><sectionB>“颜筋柳骨”指的两位楷书家时颜真卿和柳公权；而“颜张醉素”指的两位草书家时张旭和怀素</sectionB><sectionC>我国古代绘画常以朱红色和青色为主色调，故称绘画为“丹青”</sectionC><sectionD>黄公望是明代著名画家，与沈周、仇英、文征明并称为“明四家”，著名的《富春江居图》为其代表作</sectionD><answer>D</answer></item></subjects></paper>